timeseed/__init__.py
timeseed/cli.py
timeseed/config.py
timeseed/exceptions.py
timeseed/generator.py
timeseed/simple_ids.py
timeseed/utils.py
timeseed-0.1.2.dist-info/licenses/LICENSE
timeseed-0.1.2.dist-info/METADATA
timeseed-0.1.2.dist-info/WHEEL
timeseed-0.1.2.dist-info/entry_points.txt
timeseed-0.1.2.dist-info/top_level.txt
timeseed-0.1.2.dist-info/RECORD
